delphinium/__init__.py
delphinium/client.py
delphinium/dtos/__init__.py
delphinium/dtos/list.py
delphinium/dtos/search.py
delphinium/dtos/thumbnail.py
delphinium/entities/__init__.py
delphinium/entities/artist.py
delphinium/entities/base.py
delphinium/entities/character.py
delphinium/entities/file.py
delphinium/entities/galleryinfo.py
delphinium/entities/group.py
delphinium/entities/info.py
delphinium/entities/language.py
delphinium/entities/parody.py
delphinium/entities/resolved_image.py
delphinium/entities/tag.py
delphinium/entities/tags.py
delphinium/error.py
delphinium/http.py
delphinium/py.typed
delphinium/types.py
delphinium-1.5.0.dist-info/METADATA
delphinium-1.5.0.dist-info/WHEEL
delphinium-1.5.0.dist-info/licenses/LICENSE
delphinium-1.5.0.dist-info/RECORD
